qiime_tools/__init__.py
qiime_tools/biom_calc.py
qiime_tools/otu_calc.py
qiime_tools/util.py
qiime_tools/test/__init__.py
qiime_tools/test/test_qiime-tools.py
qiime_tools-1.1.2.data/data/data/pbs_job_template.pbs
qiime_tools-1.1.2.data/data/data/slurm_job_template.sbatch
qiime_tools-1.1.2.data/scripts/assign_taxonomy_by_blast_result.py
qiime_tools-1.1.2.data/scripts/barcode_filter.py
qiime_tools-1.1.2.data/scripts/biom_phyla_summary.py
qiime_tools-1.1.2.data/scripts/biom_relative_abundance.py
qiime_tools-1.1.2.data/scripts/condense_workflow.py
qiime_tools-1.1.2.data/scripts/filter_keep_otus_by_sample.py
qiime_tools-1.1.2.data/scripts/filter_rep_set.py
qiime_tools-1.1.2.data/scripts/iTol.py
qiime_tools-1.1.2.data/scripts/merge_otu_results.py
qiime_tools-1.1.2.data/scripts/multi_parallel_pick_otus.py
qiime_tools-1.1.2.data/scripts/multi_qsub.py
qiime_tools-1.1.2.data/scripts/otu_condense.py
qiime_tools-1.1.2.data/scripts/otu_to_tax_name.py
qiime_tools-1.1.2.data/scripts/PCoA_bubble.py
qiime_tools-1.1.2.data/scripts/pick_otus_condense.py
qiime_tools-1.1.2.data/scripts/primer_average.py
qiime_tools-1.1.2.data/scripts/prune_otus.py
qiime_tools-1.1.2.data/scripts/sanger_qiimify.py
qiime_tools-1.1.2.data/scripts/split_sequence_data.py
qiime_tools-1.1.2.data/scripts/transpose_biom.py
qiime_tools-1.1.2.dist-info/DESCRIPTION.rst
qiime_tools-1.1.2.dist-info/METADATA
qiime_tools-1.1.2.dist-info/metadata.json
qiime_tools-1.1.2.dist-info/RECORD
qiime_tools-1.1.2.dist-info/top_level.txt
qiime_tools-1.1.2.dist-info/WHEEL
